imagefilters/__init__.py
imagefilters/filters.py
imagefilters_apoorvamdeval-0.1.1.dist-info/licenses/LICENSE
imagefilters_apoorvamdeval-0.1.1.dist-info/METADATA
imagefilters_apoorvamdeval-0.1.1.dist-info/WHEEL
imagefilters_apoorvamdeval-0.1.1.dist-info/top_level.txt
imagefilters_apoorvamdeval-0.1.1.dist-info/RECORD
