Metadata-Version: 2.4
Name: imagefilters-apoorvamdeval
Version: 0.1.1
Summary: A simple image filtering package with Averaging, Gaussian, Weighted, and Median filters.
Author-email: Apoorva Deval <apoorvamdeval@gmail.com>
License: MIT
Classifier: Programming Language :: Python :: 3
Classifier: License :: OSI Approved :: MIT License
Classifier: Operating System :: OS Independent
Requires-Python: >=3.7
License-File: LICENSE
Requires-Dist: opencv-python
Requires-Dist: numpy
Requires-Dist: matplotlib
Dynamic: license-file
